pyviko/__init__.py
pyviko/core.py
pyviko/mutation.py
pyviko/restriction.py
pyviko-1.1.0.6.dist-info/METADATA
pyviko-1.1.0.6.dist-info/RECORD
pyviko-1.1.0.6.dist-info/WHEEL
pyviko-1.1.0.6.dist-info/top_level.txt
