Metadata-Version: 2.1
Name: pyviko
Version: 1.1.0.6
Summary: Design knockout viruses in Python
Home-page: https://github.com/louiejtaylor/pyViKO
Author: LJ Taylor
Author-email: ltaylor7@tulane.edu
License: MIT License
Platform: UNKNOWN
Classifier: Intended Audience :: Science/Research
Classifier: Environment :: Console
Classifier: Environment :: Web Environment
Classifier: License :: OSI Approved :: MIT License
Classifier: Programming Language :: Python :: 3
Classifier: Topic :: Scientific/Engineering :: Bio-Informatics
